Metadata-Version: 1.0
Name: lopy
Version: 0.0.7
Summary: Local Python package manager
Home-page: https://github.com/jo-sm/lopy
Author: Joshua Smock
Author-email: UNKNOWN
License: MIT
Platform: UNKNOWN
